matmacore/__init__.py
matmacore/mol.py
matmacore/plot.py
matmacore/utilities.py
matmacore-0.2.3.dist-info/licenses/LICENSE
matmacore-0.2.3.dist-info/METADATA
matmacore-0.2.3.dist-info/WHEEL
matmacore-0.2.3.dist-info/top_level.txt
matmacore-0.2.3.dist-info/RECORD
