Metadata-Version: 2.4
Name: matmacore
Version: 0.2.3
Summary: Add your description here
Requires-Python: >=3.12
License-File: LICENSE
Dynamic: license-file
